behave_webdriver/__init__.py
behave_webdriver/conditions.py
behave_webdriver/driver.py
behave_webdriver/fixtures.py
behave_webdriver/transformers.py
behave_webdriver/utils.py
behave_webdriver/steps/__init__.py
behave_webdriver/steps/actions.py
behave_webdriver/steps/actions_re.py
behave_webdriver/steps/expectations.py
behave_webdriver-0.3.1.dist-info/LICENSE
behave_webdriver-0.3.1.dist-info/METADATA
behave_webdriver-0.3.1.dist-info/WHEEL
behave_webdriver-0.3.1.dist-info/top_level.txt
behave_webdriver-0.3.1.dist-info/RECORD
