Metadata-Version: 2.1
Name: behave-webdriver
Version: 0.3.1
Summary: Selenium webdriver step library for behave BDD testing
Home-page: https://github.com/spyoungtech/behave-webdriver/
Author: Spencer Young
Author-email: spencer.young@spyoung.com
License: MIT
Platform: any
Classifier: Intended Audience :: Developers
Classifier: Topic :: Software Development :: Testing
Classifier: Topic :: Software Development :: Quality Assurance
Classifier: Topic :: Internet :: WWW/HTTP :: Browsers
Classifier: Topic :: Software Development :: Testing :: BDD
Classifier: Operating System :: OS Independent
Classifier: License :: OSI Approved :: MIT License
Classifier: Programming Language :: Python
Classifier: Programming Language :: Python :: 2.7
Classifier: Programming Language :: Python :: 3
Classifier: Programming Language :: Python :: 3.5
Classifier: Programming Language :: Python :: 3.6
Classifier: Programming Language :: Python :: 3.7
License-File: LICENSE
